netfile/__init__.py
netfile/netfile.py
netfile-0.1.3.dist-info/LICENSE
netfile-0.1.3.dist-info/METADATA
netfile-0.1.3.dist-info/WHEEL
netfile-0.1.3.dist-info/top_level.txt
netfile-0.1.3.dist-info/RECORD
